pyds.cpython-38-x86_64-linux-gnu.so
pyds_ext-2.0.0.dist-info/LICENSE
pyds_ext-2.0.0.dist-info/METADATA
pyds_ext-2.0.0.dist-info/WHEEL
pyds_ext-2.0.0.dist-info/top_level.txt
pyds_ext-2.0.0.dist-info/RECORD
