Metadata-Version: 2.1
Name: pyds-ext
Version: 2.0.0
Summary: Extra binding patches for nvidia deepstream.
License-File: LICENSE
